attuned-1.0.2.dist-info/METADATA
attuned-1.0.2.dist-info/WHEEL
attuned/__init__.py
attuned/__init__.pyi
attuned/__pycache__/__init__.cpython-311.pyc
attuned/__pycache__/core.cpython-311.pyc
attuned/_attuned.abi3.so
attuned/core.py
attuned/core.pyi
attuned/integrations/__init__.py
attuned/integrations/__init__.pyi
attuned/integrations/anthropic.py
attuned/integrations/anthropic.pyi
attuned/integrations/litellm.py
attuned/integrations/litellm.pyi
attuned/integrations/openai.py
attuned/integrations/openai.pyi
attuned/py.typed
attuned-1.0.2.dist-info/RECORD
