Metadata-Version: 2.4
Name: attuned
Version: 1.0.2
Classifier: Development Status :: 4 - Beta
Classifier: Intended Audience :: Developers
Classifier: License :: OSI Approved :: Apache Software License
Classifier: Programming Language :: Python :: 3
Classifier: Programming Language :: Python :: 3.9
Classifier: Programming Language :: Python :: 3.10
Classifier: Programming Language :: Python :: 3.11
Classifier: Programming Language :: Python :: 3.12
Classifier: Programming Language :: Rust
Classifier: Topic :: Scientific/Engineering :: Artificial Intelligence
Classifier: Typing :: Typed
Requires-Dist: pytest>=7.0 ; extra == 'dev'
Requires-Dist: pytest-asyncio>=0.21 ; extra == 'dev'
Requires-Dist: mypy>=1.0 ; extra == 'dev'
Provides-Extra: dev
Summary: Human state to LLM context translation - Python bindings for the Attuned framework
Keywords: llm,ai,agent,context,state,langchain,openai
Home-Page: https://github.com/JtPerez-Acle/Attuned
Author: Attuned Contributors
License: Apache-2.0
Requires-Python: >=3.9
Project-URL: Homepage, https://github.com/JtPerez-Acle/Attuned
Project-URL: Documentation, https://github.com/JtPerez-Acle/Attuned#readme
Project-URL: Repository, https://github.com/JtPerez-Acle/Attuned
Project-URL: Issues, https://github.com/JtPerez-Acle/Attuned/issues
